[
  {
    "parent": "",
    "path": "/account",
    "name": "account",
    "type": "dir",
    "icon": "DashboardOutlined",
    "title": "",
    "sort": 0,
    "link": "",
    "hidden": true,
    "status": true,
    "i18n": "account"
  },
  {
    "parent": "account",
    "path": "center",
    "name": "account-center",
    "type": "menu",
    "icon": "DashboardOutlined",
    "title": "个人中心",
    "sort": 0,
    "link": "",
    "hidden": false,
    "status": true,
    "i18n": "account-center"
  },
  {
    "parent": "",
    "path": "/dashboard",
    "name": "dashboard",
    "type": "dir",
    "icon": "HomeOutlined",
    "title": "工作空间",
    "sort": 1,
    "link": "",
    "hidden": false,
    "status": true,
    "i18n": "dashboard"
  },
  {
    "parent": "dashboard",
    "path": "console",
    "name": "dashboard-console",
    "type": "menu",
    "icon": "DashboardOutlined",
    "title": "分析页",
    "sort": 0,
    "link": "",
    "hidden": false,
    "status": true,
    "i18n": "dashboard-console"
  },{
    "parent": "dashboard",
    "path": "workspace",
    "name": "dashboard-workspace",
    "type": "menu",
    "icon": "DashboardOutlined",
    "title": "工作台",
    "sort": 0,
    "link": "",
    "hidden": false,
    "status": true,
    "i18n": "dashboard-workspace"
  },
  {
    "parent": "",
    "path": "/form",
    "name": "form",
    "type": "dir",
    "icon": "FormOutlined",
    "title": "表单页面",
    "sort": 2,
    "link": "",
    "hidden": false,
    "status": true,
    "i18n": "form"
  },
  {
    "parent": "form",
    "path": "baseForm",
    "name": "base-form",
    "type": "menu",
    "icon": "DatabaseOutlined",
    "title": "基础表单",
    "sort": 0,
    "link": "",
    "hidden": false,
    "status": true,
    "i18n": "base-form"
  },
  {
    "parent": "form",
    "path": "advancedForm",
    "name": "advanced-form",
    "type": "menu",
    "icon": "DatabaseOutlined",
    "title": "高级表单",
    "sort": 1,
    "link": "",
    "hidden": false,
    "status": true,
    "i18n": "advanced-form"
  },
  {
    "parent": "form",
    "path": "stepForm",
    "name": "step-form",
    "type": "menu",
    "icon": "DatabaseOutlined",
    "title": "分步表单",
    "sort": 1,
    "link": "",
    "hidden": false,
    "status": true,
    "i18n": "step-form"
  },
  {
    "parent": "",
    "path": "/list",
    "name": "list",
    "type": "dir",
    "icon": "UnorderedListOutlined",
    "title": "列表页面",
    "sort": 3,
    "link": "",
    "hidden": false,
    "status": true,
    "i18n": "list"
  },
  {
    "parent": "list",
    "path": "baseList",
    "name": "base-list",
    "type": "menu",
    "icon": "DatabaseOutlined",
    "title": "基础列表",
    "sort": 0,
    "link": "",
    "hidden": false,
    "status": true,
    "i18n": "base-list"
  },
  {
    "parent": "list",
    "path": "cardList",
    "name": "card-list",
    "type": "menu",
    "icon": "DatabaseOutlined",
    "title": "卡片列表",
    "sort": 1,
    "link": "",
    "hidden": false,
    "status": true,
    "i18n": "card-list"
  },
  {
    "parent": "list",
    "path": "newsList",
    "name": "news-list",
    "type": "menu",
    "icon": "DatabaseOutlined",
    "title": "图文列表",
    "sort": 2,
    "link": "",
    "hidden": false,
    "status": true,
    "i18n": "news-list"
  },
  {
    "parent": "list",
    "path": "tableList",
    "name": "table-list",
    "type": "menu",
    "icon": "DatabaseOutlined",
    "title": "查询表格",
    "sort": 3,
    "link": "",
    "hidden": false,
    "status": true,
    "i18n": "table-list"
  },
  {
    "parent": "",
    "path": "/result",
    "name": "result-menu",
    "type": "dir",
    "icon": "TagOutlined",
    "title": "结果页面",
    "sort": 4,
    "link": "",
    "hidden": false,
    "status": true,
    "i18n": "result-menu"
  },
  {
    "parent": "result-menu",
    "path": "success",
    "name": "result-success",
    "type": "menu",
    "icon": "DatabaseOutlined",
    "title": "成功",
    "sort": 0,
    "link": "",
    "hidden": false,
    "status": true,
    "i18n": "result-success"
  },
  {
    "parent": "result-menu",
    "path": "failure",
    "name": "result-failure",
    "type": "menu",
    "icon": "DatabaseOutlined",
    "title": "失败",
    "sort": 1,
    "link": "",
    "hidden": false,
    "status": true,
    "i18n": "result-failure"
  },
  {
    "parent": "result-menu",
    "path": "warning",
    "name": "result-warning",
    "type": "menu",
    "icon": "DatabaseOutlined",
    "title": "警告",
    "sort": 1,
    "link": "",
    "hidden": false,
    "status": true,
    "i18n": "result-warning"
  },
  {
    "parent": "result-menu",
    "path": "info",
    "name": "result-info",
    "type": "menu",
    "icon": "DatabaseOutlined",
    "title": "详情",
    "sort": 1,
    "link": "",
    "hidden": false,
    "status": true,
    "i18n": "result-info"
  },
  {
    "parent": "",
    "path": "/error",
    "name": "error",
    "type": "dir",
    "icon": "StopOutlined",
    "title": "错误页面",
    "sort": 5,
    "link": "",
    "hidden": false,
    "status": true,
    "i18n": "error"
  },
  {
    "parent": "error",
    "path": "403",
    "name": "error-403",
    "type": "menu",
    "icon": "DatabaseOutlined",
    "title": "403",
    "sort": 0,
    "link": "",
    "hidden": false,
    "status": true,
    "i18n": "error-403"
  },
  {
    "parent": "error",
    "path": "404",
    "name": "error-404",
    "type": "menu",
    "icon": "DatabaseOutlined",
    "title": "404",
    "sort": 1,
    "link": "",
    "hidden": false,
    "status": true,
    "i18n": "error-404"
  },
  {
    "parent": "error",
    "path": "500",
    "name": "error-500",
    "type": "menu",
    "icon": "DatabaseOutlined",
    "title": "500",
    "sort": 2,
    "link": "",
    "hidden": false,
    "status": true,
    "i18n": "error-500"
  },
  {
    "parent": "",
    "path": "/permission",
    "name": "permission",
    "type": "menu",
    "icon": "DatabaseOutlined",
    "title": "系统权限",
    "sort": 6,
    "link": "",
    "hidden": false,
    "status": true,
    "i18n": "permission"
  },
  {
    "parent": "permission",
    "path": "permission-test",
    "name": "permission-test",
    "type": "menu",
    "icon": "DatabaseOutlined",
    "title": "权限页面",
    "sort": 7,
    "link": "",
    "hidden": false,
    "status": true,
    "i18n": "permission-test"
  }
]
